mathlogic/__init__.py
mathlogic/leaderboardutils.py
mathlogic-1.2.3.dist-info/DESCRIPTION.rst
mathlogic-1.2.3.dist-info/METADATA
mathlogic-1.2.3.dist-info/RECORD
mathlogic-1.2.3.dist-info/WHEEL
mathlogic-1.2.3.dist-info/metadata.json
mathlogic-1.2.3.dist-info/top_level.txt
